pam/__init__.py
pam/activity.py
pam/cli.py
pam/core.py
pam/location.py
pam/py.typed
pam/scoring.py
pam/utils.py
pam/variables.py
pam/vehicles.py
pam/array/__init__.py
pam/array/decode.py
pam/array/distance.py
pam/array/encode.py
pam/fixtures/dtd/electric_vehicles_v1.dtd
pam/fixtures/dtd/objectattributes_v1.dtd
pam/fixtures/dtd/population_v5.dtd
pam/fixtures/dtd/population_v6.dtd
pam/fixtures/dtd/vehicleDefinitions_v2.0.xsd
pam/operations/__init__.py
pam/operations/combine.py
pam/operations/cropping.py
pam/optimise/__init__.py
pam/optimise/grid.py
pam/optimise/random.py
pam/planner/__init__.py
pam/planner/choice_location.py
pam/planner/clustering.py
pam/planner/encoder.py
pam/planner/ipf.py
pam/planner/od.py
pam/planner/utils_planner.py
pam/planner/zones.py
pam/plot/__init__.py
pam/plot/plans.py
pam/plot/stats.py
pam/policy/__init__.py
pam/policy/filters.py
pam/policy/modifiers.py
pam/policy/policies.py
pam/policy/probability_samplers.py
pam/read/__init__.py
pam/read/diary.py
pam/read/matsim.py
pam/report/__init__.py
pam/report/benchmarks.py
pam/report/stringify.py
pam/report/summary.py
pam/samplers/__init__.py
pam/samplers/attributes.py
pam/samplers/basic.py
pam/samplers/facility.py
pam/samplers/population.py
pam/samplers/spatial.py
pam/samplers/time.py
pam/samplers/tour.py
pam/write/__init__.py
pam/write/diary.py
pam/write/matrices.py
pam/write/matsim.py
cml_pam-0.3.2.dist-info/LICENSE
cml_pam-0.3.2.dist-info/METADATA
cml_pam-0.3.2.dist-info/WHEEL
cml_pam-0.3.2.dist-info/entry_points.txt
cml_pam-0.3.2.dist-info/top_level.txt
cml_pam-0.3.2.dist-info/RECORD
