Metadata-Version: 2.1
Name: cml-pam
Version: 0.3.2
Summary: The Population activity Modeller (PAM) is a python API for activity sequence modelling.
Author-email: Fred Shone <fred.shone@arup.com>
Maintainer-email: Michael Fitzmaurice <michael.fitzmaurice@arup.com>, Kasia Kozlowska <kasia.kozlowska@arup.com>, Theodore Chatziioannou <theodore.chatziioannou@arup.com>, Bryn Pickering <17178478+brynpickering@users.noreply.github.com>
License: MIT
Project-URL: repository, https://github.com/arup-group/pam
Project-URL: documentation, https://arup-group.github.io/pam
Project-URL: changelog, https://github.com/arup-group/pam/blob/main/CHANGELOG.md
Keywords: agent-based modelling,sequence model,matsim
Classifier: Development Status :: 3 - Alpha
Classifier: Programming Language :: Python :: 3
Classifier: Operating System :: OS Independent
Requires-Python: >=3.8
License-File: LICENSE
Requires-Dist: click <9
Requires-Dist: gdal >=3.5
Requires-Dist: geopandas <0.15,>=0.13
Requires-Dist: importlib-resources <7,>=6
Requires-Dist: ipykernel <7
Requires-Dist: lxml <5
Requires-Dist: matplotlib <4,>=3
Requires-Dist: numpy <2,>=1
Requires-Dist: pandas <3,>=1.5
Requires-Dist: plotly <6,>=4
Requires-Dist: prettytable <4,>=3
Requires-Dist: python-Levenshtein <0.26,>=0.21
Requires-Dist: rich <14,>=12
Requires-Dist: Rtree <2,>=1
Requires-Dist: s2sphere <0.3
Requires-Dist: scikit-learn <2,>=1.2
Requires-Dist: shapely <3,>=1
Requires-Dist: xlrd <3,>=2
Provides-Extra: dev
Requires-Dist: cruft <3,>=2 ; extra == 'dev'
Requires-Dist: jupyter <2 ; extra == 'dev'
Requires-Dist: mike <3,>=2 ; extra == 'dev'
Requires-Dist: mkdocs <2 ; extra == 'dev'
Requires-Dist: mkdocs-material <10,>=9.4 ; extra == 'dev'
Requires-Dist: mkdocs-click <0.7 ; extra == 'dev'
Requires-Dist: mkdocs-jupyter <0.25 ; extra == 'dev'
Requires-Dist: mkdocstrings-python <2 ; extra == 'dev'
Requires-Dist: nbmake <2,>=1.5.1 ; extra == 'dev'
Requires-Dist: pre-commit <4 ; extra == 'dev'
Requires-Dist: pytest <9,>=8 ; extra == 'dev'
Requires-Dist: pytest-cov <5 ; extra == 'dev'
Requires-Dist: pytest-mock <4 ; extra == 'dev'
Requires-Dist: pytest-timeout <3 ; extra == 'dev'
Requires-Dist: pytest-xdist <4 ; extra == 'dev'
